alpinepkgs/__init__.py
alpinepkgs/packages.py
alpinepkgs-2.0.0.dist-info/LICENSE
alpinepkgs-2.0.0.dist-info/METADATA
alpinepkgs-2.0.0.dist-info/WHEEL
alpinepkgs-2.0.0.dist-info/top_level.txt
alpinepkgs-2.0.0.dist-info/RECORD
