Metadata-Version: 2.1
Name: alpinepkgs
Version: 2.0.0
Home-page: https://github.com/ludeeus/alpinepkgs
Author: Joakim Sorensen
Author-email: ludeeus@gmail.com
Classifier: Programming Language :: Python :: 3
Classifier: License :: OSI Approved :: MIT License
Classifier: Operating System :: OS Independent
License-File: LICENSE
Requires-Dist: requests
